picoptim/__init__.py
picoptim/_helper.py
picoptim/fun_evals.py
picoptim/optim.py
picoptim/optim_result.py
picoptim/optimizer.py
picoptim/types.py
picoptim/exhaustive/__init__.py
picoptim/exhaustive/brute_force.py
picoptim/exhaustive/grid_search/__init__.py
picoptim/exhaustive/grid_search/grid_search.py
picoptim/fun_format/__init__.py
picoptim/fun_format/bound_support.py
picoptim/generative_optim/__init__.py
picoptim/generative_optim/cma_optimizer.py
picoptim/generative_optim/gen_optim.py
picoptim/generative_optim/mh_optimizer.py
picoptim/gradient_optim/__init__.py
picoptim/gradient_optim/adam.py
picoptim/gradient_optim/gradient_enhancer.py
picoptim/gradient_optim/gradient_optimizer.py
picoptim/gradient_optim/nesterov.py
picoptim/search/__init__.py
picoptim/search/dichoto.py
picoptim-0.0.4.dist-info/LICENSE
picoptim-0.0.4.dist-info/METADATA
picoptim-0.0.4.dist-info/WHEEL
picoptim-0.0.4.dist-info/top_level.txt
picoptim-0.0.4.dist-info/RECORD
